convert_ms.py
convert_ms-0.0.5.dist-info/WHEEL
convert_ms-0.0.5.dist-info/METADATA
convert_ms-0.0.5.dist-info/RECORD
