Metadata-Version: 2.1
Name: convert-ms
Version: 0.0.5
Summary: Convert a time units to seconds
Home-page: https://github.com/Forzy8/convert_ms
License: Apache-2.0
Author: Forzy
Author-email: nikita11tzby@gmail.com
Requires-Python: >=3.6,<4.0
Classifier: License :: OSI Approved :: Apache Software License
Classifier: Programming Language :: Python :: 3
Classifier: Programming Language :: Python :: 3.10
Classifier: Programming Language :: Python :: 3.6
Classifier: Programming Language :: Python :: 3.7
Classifier: Programming Language :: Python :: 3.8
Classifier: Programming Language :: Python :: 3.9
Project-URL: Repository, https://github.com/Forzy8/convert_ms
